datacondabc/__init__.py
datacondabc/models.py
datacondabc/nnets.py
datacondabc/train_network.py
datacondabc/utilities.py
datacondabc/samplers/__init__.py
datacondabc/samplers/samplers.py
datacondabc/simulators/__init__.py
datacondabc/simulators/approxsim.py
datacondabc/simulators/exactsim.py
datacondabc-0.1.dist-info/METADATA
datacondabc-0.1.dist-info/WHEEL
datacondabc-0.1.dist-info/top_level.txt
datacondabc-0.1.dist-info/RECORD
