Metadata-Version: 2.1
Name: datacondabc
Version: 0.1
Summary: Bayesian inference for SDE models using ABC-SMC
Home-page: UNKNOWN
Author: Petar Jovanovski
Author-email: <petarj@chalmers.se>
License: UNKNOWN
Keywords: python,abc,sde
Platform: UNKNOWN
Requires-Dist: numpy
Requires-Dist: scipy
Requires-Dist: numba
Requires-Dist: pot
Requires-Dist: torch
Requires-Dist: pytorch-lightning
